.env
.gitignore
LICENSE
MANIFEST.in
README.rst
dev-requirements.txt
requirements.txt
setup.cfg
setup.py
tasks.py
beetsplug/__init__.py
beetsplug/beetzbox.py
beetzbox.egg-info/PKG-INFO
beetzbox.egg-info/SOURCES.txt
beetzbox.egg-info/dependency_links.txt
beetzbox.egg-info/namespace_packages.txt
beetzbox.egg-info/requires.txt
beetzbox.egg-info/top_level.txt
tests/conftest.py
tests/test_beetsplug.py