Metadata-Version: 1.1
Name: beetzbox
Version: 0.1.0.dev0
Summary: A Beets plugin to integrate it with the SqueezeBox eco-system
Home-page: https://github.com/jhermann/beetzbox
Author: Jürgen Hermann
Author-email: jh@web.de
License: MIT
Keywords: squeezebox,music,beets,beets.plugin,media.management
Platform: UNKNOWN
Classifier: Development Status :: 3 - Alpha
Classifier: Programming Language :: Python
Classifier: Programming Language :: Python :: 3
Classifier: Programming Language :: Python :: 3.5
Classifier: Environment :: Console
Classifier: Intended Audience :: End Users/Desktop
Classifier: License :: OSI Approved :: MIT License
Classifier: Operating System :: OS Independent
Classifier: Topic :: Multimedia :: Sound/Audio
Classifier: Topic :: Utilities
